<?xml version="1.0" encoding="utf-8"?>
<resources>
    <string name="config_batterymeterBoltPath">
        M4.73,9.67L3.55,9.66C3.32,9.65,3.26,9.96,3.55,10.12L5.30,11.06C5.66,11.23,6.02,10.91,6.02,10.33L7.20,10.34C7.43,10.35,7.49,10.04,7.20,9.88L5.45,8.94C5.09,8.77,4.73,9.09,4.73,9.67
    </string>
    <string name="config_batterymeterFillMask">M1.53,7.08L9.28,7.08A1.49 1.49 0 0 1
        10.77,8.57L10.77,11.43A1.49 1.49 0 0 1 9.28,12.92L1.53,12.92A1.49 1.49 0 0 1
        0.04,11.43L0.04,8.57A1.49 1.49 0 0 1 1.53,7.08zM0.53,8.57L0.53,11.45A1.00 1.00 0 0 0
        1.53,12.45L9.28,12.45A1.00 1.00 0 0 0 10.29,11.45L10.29,8.57A1.00 1.00 0 0 0
        9.28,7.57L1.53,7.57A1.00 1.00 0 0 0
        0.53,8.57zM11.25,10.97C12.20,10.91,12.20,9.09,11.25,9.03L11.25,10.97zM1.02,8.79L1.02,11.20A0.75
        0.75 0 0 0 1.77,11.95L9.04,11.95A0.75 0.75 0 0 0 9.78,11.20L9.78,8.79A0.75 0.75 0 0 0
        9.04,8.04L1.77,8.04A0.75 0.75 0 0 0
        1.02,8.79zM2.94,9.52C3.21,9.52,3.43,9.73,3.43,10.00C3.43,10.27,3.21,10.49,2.94,10.49C2.67,10.49,2.45,10.27,2.45,10.00C2.45,9.73,2.67,9.52,2.94,9.52zM7.81,9.52C8.08,9.52,8.30,9.73,8.30,10.00C8.30,10.27,8.08,10.49,7.81,10.49C7.54,10.49,7.32,10.27,7.32,10.00C7.32,9.73,7.54,9.52,7.81,9.52zM6.11,10.00C6.02,10.98,4.73,10.98,4.64,10.00C4.67,9.68,5.10,9.68,5.13,10.00C5.11,10.33,5.64,10.33,5.62,10.00C5.65,9.68,6.08,9.68,6.11,10.00z
    </string>
    <string name="config_batterymeterPerimeterPath">M1.53,7.08L9.28,7.08A1.49 1.49 0 0 1
        10.77,8.57L10.77,11.43A1.49 1.49 0 0 1 9.28,12.92L1.53,12.92A1.49 1.49 0 0 1
        0.04,11.43L0.04,8.57A1.49 1.49 0 0 1 1.53,7.08zM0.53,8.57L0.53,11.45A1.00 1.00 0 0 0
        1.53,12.45L9.28,12.45A1.00 1.00 0 0 0 10.29,11.45L10.29,8.57A1.00 1.00 0 0 0
        9.28,7.57L1.53,7.57A1.00 1.00 0 0 0
        0.53,8.57zM11.25,10.97C12.20,10.91,12.20,9.09,11.25,9.03L11.25,10.97zM1.02,8.79L1.02,11.20A0.75
        0.75 0 0 0 1.77,11.95L9.04,11.95A0.75 0.75 0 0 0 9.78,11.20L9.78,8.79A0.75 0.75 0 0 0
        9.04,8.04L1.77,8.04A0.75 0.75 0 0 0
        1.02,8.79zM2.94,9.52C3.21,9.52,3.43,9.73,3.43,10.00C3.43,10.27,3.21,10.49,2.94,10.49C2.67,10.49,2.45,10.27,2.45,10.00C2.45,9.73,2.67,9.52,2.94,9.52zM7.81,9.52C8.08,9.52,8.30,9.73,8.30,10.00C8.30,10.27,8.08,10.49,7.81,10.49C7.54,10.49,7.32,10.27,7.32,10.00C7.32,9.73,7.54,9.52,7.81,9.52zM6.11,10.00C6.02,10.98,4.73,10.98,4.64,10.00C4.67,9.68,5.10,9.68,5.13,10.00C5.11,10.33,5.64,10.33,5.62,10.00C5.65,9.68,6.08,9.68,6.11,10.00z
    </string>
    <string name="config_batterymeterPowersavePath">M1.53,7.08L9.28,7.08A1.49 1.49 0 0 1
        10.77,8.57L10.77,11.43A1.49 1.49 0 0 1 9.28,12.92L1.53,12.92A1.49 1.49 0 0 1
        0.04,11.43L0.04,8.57A1.49 1.49 0 0 1 1.53,7.08zM0.53,8.57L0.53,11.45A1.00 1.00 0 0 0
        1.53,12.45L9.28,12.45A1.00 1.00 0 0 0 10.29,11.45L10.29,8.57A1.00 1.00 0 0 0
        9.28,7.57L1.53,7.57A1.00 1.00 0 0 0
        0.53,8.57zM11.25,10.97C12.20,10.91,12.20,9.09,11.25,9.03L11.25,10.97zM1.02,8.79L1.02,11.20A0.75
        0.75 0 0 0 1.77,11.95L9.04,11.95A0.75 0.75 0 0 0 9.78,11.20L9.78,8.79A0.75 0.75 0 0 0
        9.04,8.04L1.77,8.04A0.75 0.75 0 0 0
        1.02,8.79zM2.94,9.52C3.21,9.52,3.43,9.73,3.43,10.00C3.43,10.27,3.21,10.49,2.94,10.49C2.67,10.49,2.45,10.27,2.45,10.00C2.45,9.73,2.67,9.52,2.94,9.52zM7.81,9.52C8.08,9.52,8.30,9.73,8.30,10.00C8.30,10.27,8.08,10.49,7.81,10.49C7.54,10.49,7.32,10.27,7.32,10.00C7.32,9.73,7.54,9.52,7.81,9.52zM6.11,10.00C6.02,10.98,4.73,10.98,4.64,10.00C4.67,9.68,5.10,9.68,5.13,10.00C5.11,10.33,5.64,10.33,5.62,10.00C5.65,9.68,6.08,9.68,6.11,10.00z
    </string>
    <bool name="config_batterymeterDualTone">true</bool>
</resources>
